rtl/core/pc_logic.v
module pc_logic (
    input  wire        clk,
    input  wire        reset,
    input  wire        stall,

    input  wire        branch_taken,
    input  wire [31:0] branch_target,

    input  wire        jump,
    input  wire [31:0] jump_target,

    output reg  [31:0] pc
);

    always @(posedge clk or posedge reset) begin
        if (reset) begin
            pc <= 32'd0;
        end
        else if (stall) begin
            pc <= pc;
        end
        else if (jump) begin
            pc <= jump_target;
        end
        else if (branch_taken) begin
            pc <= branch_target;
        end
        else begin
            pc <= pc + 32'd4;
        end
    end

endmodule

tb/pc_logic_tb.v
`timescale 1ns/1ps

module pc_logic_tb;

    reg clk;
    reg reset;
    reg stall;

    reg branch_taken;
    reg [31:0] branch_target;

    reg jump;
    reg [31:0] jump_target;

    wire [31:0] pc;

    pc_logic uut (
        .clk(clk),
        .reset(reset),
        .stall(stall),
        .branch_taken(branch_taken),
        .branch_target(branch_target),
        .jump(jump),
        .jump_target(jump_target),
        .pc(pc)
    );

    always #5 clk = ~clk;

    initial begin
        clk = 0;
        reset = 1;
        stall = 0;
        branch_taken = 0;
        branch_target = 0;
        jump = 0;
        jump_target = 0;

        #10 reset = 0;

        // Normal PC increment
        #20;

        // Stall test
        stall = 1;
        #10;
        stall = 0;

        // Branch test
        branch_taken = 1;
        branch_target = 32'd100;
        #10;
        branch_taken = 0;

        // Jump test
        jump = 1;
        jump_target = 32'd200;
        #10;
        jump = 0;

        #20;

        $finish;
    end

    initial begin
        $monitor(
            "Time=%0t | PC=%d | stall=%b | branch=%b | jump=%b",
            $time, pc, stall, branch_taken, jump
        );
    end

    initial begin
        $dumpfile("pc_logic_tb.vcd");
        $dumpvars(0, pc_logic_tb);
    end

endmodule

pc_logic_tb.vcd
$date
	Sun Jun 14 09:21:30 2026
$end
$version
	Icarus Verilog
$end
$timescale
	1ps
$end
$scope module pc_logic_tb $end
$var wire 32 ! pc [31:0] $end
$var reg 1 " branch_taken $end
$var reg 32 # branch_target [31:0] $end
$var reg 1 $ clk $end
$var reg 1 % jump $end
$var reg 32 & jump_target [31:0] $end
$var reg 1 ' reset $end
$var reg 1 ( stall $end
$scope module uut $end
$var wire 1 " branch_taken $end
$var wire 32 ) branch_target [31:0] $end
$var wire 1 $ clk $end
$var wire 1 % jump $end
$var wire 32 * jump_target [31:0] $end
$var wire 1 ' reset $end
$var wire 1 ( stall $end
$var reg 32 + pc [31:0] $end
$upscope $end
$upscope $end
$enddefinitions $end
$comment Show the parameter values. $end
$dumpall
$end
#0
$dumpvars
b0 +
b0 *
b0 )
0(
1'
b0 &
0%
0$
b0 #
0"
b0 !
$end
#5000
1$
#10000
0$
0'
#15000
b100 !
b100 +
1$
#20000
0$
#25000
b1000 !
b1000 +
1$
#30000
0$
1(
#35000
1$
#40000
0$
b1100100 #
b1100100 )
1"
0(
#45000
b1100100 !
b1100100 +
1$
#50000
0$
b11001000 &
b11001000 *
1%
0"
#55000
b11001000 !
b11001000 +
1$
#60000
0$
0%
#65000
b11001100 !
b11001100 +
1$
#70000
0$
#75000
b11010000 !
b11010000 +
1$
