rtl/core/control_unit.v
// =============================================================================
// control_unit.v - Bộ giải mã lệnh RISC-V (RV32I Subset)
//
// Input:  instruction[31:0] - Mã lệnh 32-bit từ Instruction Memory
// Output: Tất cả tín hiệu điều khiển cho ALU, RegFile, Memory, PC
//
// Hỗ trợ: R-type, I-type, S-type, B-type, U-type, J-type
// =============================================================================
`timescale 1ns / 1ps

module control_unit (
    input  wire [31:0] instruction,

    // --- Tín hiệu điều khiển ---
    output reg         reg_write,    // Register File
    output reg         alu_src,      // B: 0=rs2, 1=immediate
    output reg  [3:0]  alu_control,  // Mã phép toán ALU

    output reg         mem_read,     // LW
    output reg         mem_write,    // SW
    output reg         mem_to_reg,   // rd: 0=ALU, 1=mem_data

    output reg         branch,       // Branch
    output reg  [2:0]  branch_type,  // funct3 (BEQ=000, BNE=001, BLT=100, BGE=101)

    output reg         jump,         // JAL/JALR
    output reg         jalr,         // JALR
    output reg         lui,          // LUI
    output reg         auipc,        // AUIPC
    output reg         mem_lr,       // Load-Reserved
    output reg         mem_sc,       // Store-Conditional

    output reg         mem_amo,      // Là lệnh AMO?
    output reg  [3:0]  amo_op,       // Mã phép toán AMO

    // --- Immediate Generator ---
    output reg  [31:0] imm,          // Giá trị immediate (sign-extended)

    // --- Địa chỉ thanh ghi ---
    output wire [4:0]  rs1_addr,     // Source register 1
    output wire [4:0]  rs2_addr,     // Source register 2
    output wire [4:0]  rd_addr       // Destination register
);

    // =========================================================================
    // Trích xuất các trường từ instruction
    // =========================================================================
    wire [6:0] opcode = instruction[6:0];
    wire [2:0] funct3 = instruction[14:12];
    wire [6:0] funct7 = instruction[31:25];
    wire [4:0] funct5 = instruction[31:27];

    assign rs1_addr = instruction[19:15];
    assign rs2_addr = instruction[24:20];
    assign rd_addr  = instruction[11:7];

    // =========================================================================
    // Opcode definitions (RISC-V standard)
    // =========================================================================
    localparam OP_R_TYPE  = 7'b0110011;  // ADD, SUB, AND, OR, XOR, SLL, SRL, SLT
    localparam OP_I_TYPE  = 7'b0010011;  // ADDI, ANDI, ORI, XORI, SLTI, SLLI, SRLI
    localparam OP_LOAD    = 7'b0000011;  // LW
    localparam OP_STORE   = 7'b0100011;  // SW
    localparam OP_BRANCH  = 7'b1100011;  // BEQ, BNE, BLT, BGE
    localparam OP_JAL     = 7'b1101111;  // JAL
    localparam OP_JALR    = 7'b1100111;  // JALR
    localparam OP_LUI     = 7'b0110111;  // LUI
    localparam OP_AUIPC   = 7'b0010111;  // AUIPC
    localparam OP_AMO     = 7'b0101111;  // AMO (LR, SC, AMO)

    // =========================================================================
    // ALU control codes (khớp với alu.v)
    // =========================================================================
    localparam ALU_AND = 4'b0000;
    localparam ALU_OR  = 4'b0001;
    localparam ALU_ADD = 4'b0010;
    localparam ALU_SLL = 4'b0011;
    localparam ALU_XOR = 4'b0100;
    localparam ALU_SRL = 4'b0101;
    localparam ALU_SUB = 4'b0110;
    localparam ALU_SLT = 4'b0111;

    // =========================================================================
    // Immediate Generator
    // Tạo giá trị immediate dựa trên instruction type, sign-extended 32-bit
    // =========================================================================
    always @(*) begin
        case (opcode)
            // I-type: imm[11:0] = instruction[31:20]
            OP_I_TYPE, OP_LOAD, OP_JALR:
                imm = {{20{instruction[31]}}, instruction[31:20]};

            // AMO: Không dùng imm cho tính địa chỉ (imm = 0), rs1 chứa địa chỉ
            OP_AMO:
                imm = 32'd0;

            // S-type: imm[11:0] = {instruction[31:25], instruction[11:7]}
            OP_STORE:
                imm = {{20{instruction[31]}}, instruction[31:25], instruction[11:7]};

            // B-type: imm[12:1] = {[31], [7], [30:25], [11:8]}
            OP_BRANCH:
                imm = {{19{instruction[31]}}, instruction[31], instruction[7],
                        instruction[30:25], instruction[11:8], 1'b0};

            // U-type: imm[31:12] = instruction[31:12]
            OP_LUI, OP_AUIPC:
                imm = {instruction[31:12], 12'b0};

            // J-type: imm[20:1] = {[31], [19:12], [20], [30:21]}
            OP_JAL:
                imm = {{11{instruction[31]}}, instruction[31], instruction[19:12],
                        instruction[20], instruction[30:21], 1'b0};

            default:
                imm = 32'd0;
        endcase
    end

    // =========================================================================
    // Main Decoder: opcode → control signals
    // =========================================================================
    always @(*) begin
        // Mặc định: tất cả tắt
        reg_write   = 1'b0;
        alu_src     = 1'b0;
        alu_control = ALU_ADD;
        mem_read    = 1'b0;
        mem_write   = 1'b0;
        mem_to_reg  = 1'b0;
        branch      = 1'b0;
        branch_type = 3'b000;
        jump        = 1'b0;
        jalr        = 1'b0;
        lui         = 1'b0;
        auipc       = 1'b0;
        mem_lr      = 1'b0;
        mem_sc      = 1'b0;
        mem_amo     = 1'b0;
        amo_op      = 4'd0;

        case (opcode)
            // =================================================================
            // R-type: ADD, SUB, AND, OR, XOR, SLL, SRL, SLT
            // =================================================================
            OP_R_TYPE: begin
                reg_write = 1'b1;
                alu_src   = 1'b0;  // Toán hạng B = rs2

                case (funct3)
                    3'b000: alu_control = (funct7[5]) ? ALU_SUB : ALU_ADD; // ADD/SUB
                    3'b001: alu_control = ALU_SLL;  // SLL
                    3'b010: alu_control = ALU_SLT;  // SLT
                    3'b100: alu_control = ALU_XOR;  // XOR
                    3'b101: alu_control = ALU_SRL;  // SRL
                    3'b110: alu_control = ALU_OR;   // OR
                    3'b111: alu_control = ALU_AND;  // AND
                    default: alu_control = ALU_ADD;
                endcase
            end

            // =================================================================
            // I-type ALU: ADDI, ANDI, ORI, XORI, SLTI, SLLI, SRLI
            // =================================================================
            OP_I_TYPE: begin
                reg_write = 1'b1;
                alu_src   = 1'b1;  // Toán hạng B = immediate

                case (funct3)
                    3'b000: alu_control = ALU_ADD;  // ADDI
                    3'b001: alu_control = ALU_SLL;  // SLLI
                    3'b010: alu_control = ALU_SLT;  // SLTI
                    3'b100: alu_control = ALU_XOR;  // XORI
                    3'b101: alu_control = ALU_SRL;  // SRLI
                    3'b110: alu_control = ALU_OR;   // ORI
                    3'b111: alu_control = ALU_AND;  // ANDI
                    default: alu_control = ALU_ADD;
                endcase
            end

            // =================================================================
            // Load: LW (rd = mem[rs1 + imm])
            // =================================================================
            OP_LOAD: begin
                reg_write   = 1'b1;
                alu_src     = 1'b1;   // ALU tính địa chỉ: rs1 + imm
                alu_control = ALU_ADD;
                mem_read    = 1'b1;
                mem_to_reg  = 1'b1;   // Ghi mem data vào rd
            end

            // =================================================================
            // Store: SW (mem[rs1 + imm] = rs2)
            // =================================================================
            OP_STORE: begin
                alu_src     = 1'b1;   // ALU tính địa chỉ: rs1 + imm
                alu_control = ALU_ADD;
                mem_write   = 1'b1;
            end

            // =================================================================
            // Branch: BEQ, BNE, BLT, BGE
            // =================================================================
            OP_BRANCH: begin
                alu_src     = 1'b0;
                alu_control = ALU_SUB;  // So sánh bằng phép trừ
                branch      = 1'b1;
                branch_type = funct3;   // 000=BEQ, 001=BNE, 100=BLT, 101=BGE
            end

            // =================================================================
            // JAL: rd = PC+4, PC = PC + imm
            // =================================================================
            OP_JAL: begin
                reg_write = 1'b1;
                jump      = 1'b1;
            end

            // =================================================================
            // JALR: rd = PC+4, PC = (rs1 + imm) & ~1
            // =================================================================
            OP_JALR: begin
                reg_write   = 1'b1;
                alu_src     = 1'b1;
                alu_control = ALU_ADD;
                jump        = 1'b1;
                jalr        = 1'b1;
            end

            // =================================================================
            // LUI: rd = imm << 12 (đã shift trong immediate generator)
            // =================================================================
            OP_LUI: begin
                reg_write = 1'b1;
                lui       = 1'b1;
            end

            // =================================================================
            // AUIPC: rd = PC + (imm << 12)
            // =================================================================
            OP_AUIPC: begin
                reg_write = 1'b1;
                auipc     = 1'b1;
            end

            // =================================================================
            // Atomic (A-Extension): LR, SC, AMO
            // =================================================================
            OP_AMO: begin
                alu_src     = 1'b1;   // ALU tính địa chỉ: rs1 + 0 (imm = 0)
                alu_control = ALU_ADD;
                
                case (funct5)
                    5'b00010: begin // LR.W
                        mem_lr    = 1'b1;
                        reg_write = 1'b1;
                    end
                    5'b00011: begin // SC.W
                        mem_sc    = 1'b1;
                        reg_write = 1'b1; // Kết quả SC (0 hoặc 1) ghi vào rd
                    end
                    default: begin  // Các lệnh AMO khác
                        mem_amo   = 1'b1;
                        reg_write = 1'b1; // Giá trị cũ ghi vào rd
                        // Map funct5 sang amo_op cho bus_ctrl
                        case (funct5)
                            5'b00001: amo_op = 4'd0; // AMO_SWAP
                            5'b00000: amo_op = 4'd1; // AMO_ADD
                            5'b01100: amo_op = 4'd2; // AMO_AND
                            5'b01010: amo_op = 4'd3; // AMO_OR
                            5'b00100: amo_op = 4'd4; // AMO_XOR
                            5'b10100: amo_op = 4'd5; // AMO_MAX
                            5'b11100: amo_op = 4'd6; // AMO_MAXU
                            5'b10000: amo_op = 4'd7; // AMO_MIN
                            5'b11000: amo_op = 4'd8; // AMO_MINU
                            default:  amo_op = 4'd0;
                        endcase
                    end
                endcase
            end

            default: ; // NOP (tất cả outputs đã mặc định = 0)
        endcase
    end

endmodule

tb/pipline_reg_tb/tb_control_unit.v
`timescale 1ns / 1ps

module tb_control_unit;

    // --- Inputs ---
    reg [31:0] instruction;

    // --- Outputs ---
    wire        reg_write;
    wire        alu_src;
    wire [3:0]  alu_control;
    wire        mem_read;
    wire        mem_write;
    wire        mem_to_reg;
    wire        branch;
    wire [2:0]  branch_type;
    wire        jump;
    wire        jalr;
    wire        lui;
    wire        auipc;
    wire        mem_lr;
    wire        mem_sc;
    wire        mem_amo;
    wire [3:0]  amo_op;
    wire [31:0] imm;
    wire [4:0]  rs1_addr;
    wire [4:0]  rs2_addr;
    wire [4:0]  rd_addr;

    // --- Instantiate UUT (Unit Under Test) ---
    control_unit uut (
        .instruction (instruction),
        .reg_write   (reg_write),
        .alu_src     (alu_src),
        .alu_control (alu_control),
        .mem_read    (mem_read),
        .mem_write   (mem_write),
        .mem_to_reg  (mem_to_reg),
        .branch      (branch),
        .branch_type (branch_type),
        .jump        (jump),
        .jalr        (jalr),
        .lui         (lui),
        .auipc       (auipc),
        .mem_lr      (mem_lr),
        .mem_sc      (mem_sc),
        .mem_amo     (mem_amo),
        .amo_op      (amo_op),
        .imm         (imm),
        .rs1_addr    (rs1_addr),
        .rs2_addr    (rs2_addr),
        .rd_addr     (rd_addr)
    );

    // =========================================================================
    // KHỐI GHI FILE SÓNG DÀNH CHO GTKWAVE
    // =========================================================================
    initial begin
        $dumpfile("control_unit_waveform.vcd");
        $dumpvars(0, tb_control_unit);
    end

    // --- Test Stimulus ---
    initial begin
        $display("=========================================================================");
        $display("STARTING CONTROL UNIT TESTING WITH REAL INSTRUCTION HEX");
        $display("=========================================================================");

        //----------------------------------------------------------------------
        // 1. Lệnh R-type: ADD x3, x1, x2  (Mã máy: 002081B3)
        //----------------------------------------------------------------------
        instruction = 32'h002081B3; 
        #10;
        $display("[ADD]    reg_write=%b, alu_src=%b, alu_ctrl=%b, rs1=%d, rs2=%d, rd=%d", 
                  reg_write, alu_src, alu_control, rs1_addr, rs2_addr, rd_addr);

        //----------------------------------------------------------------------
        // 2. Lệnh I-type: ADDI x5, x4, -10 (Mã máy: FF620293)
        //----------------------------------------------------------------------
        instruction = 32'hFF620293; 
        #10;
        $display("[ADDI]   reg_write=%b, alu_src=%b, alu_ctrl=%b, imm=%d (Hex: %h)", 
                  reg_write, alu_src, alu_control, $signed(imm), imm);

        //----------------------------------------------------------------------
        // 3. Lệnh Load: LW x6, 4(x5)      (Mã máy: 0042A303)
        //----------------------------------------------------------------------
        instruction = 32'h0042A303; 
        #10;
        $display("[LW]     reg_write=%b, mem_read=%b, mem_to_reg=%b, imm=%d", 
                  reg_write, mem_read, mem_to_reg, imm);

        //----------------------------------------------------------------------
        // 4. Lệnh Store: SW x7, 8(x5)     (Mã máy: 0072A423)
        //----------------------------------------------------------------------
        instruction = 32'h0072A423; 
        #10;
        $display("[SW]     mem_write=%b, alu_src=%b, imm=%d", 
                  mem_write, alu_src, imm);

        //----------------------------------------------------------------------
        // 5. Lệnh Branch: BNE x1, x2, 16  (Mã máy: 00209863)
        //----------------------------------------------------------------------
        instruction = 32'h00209863; 
        #10;
        $display("[BNE]    branch=%b, branch_type=%b, alu_ctrl=%b, imm=%d", 
                  branch, branch_type, alu_control, $signed(imm));

        //----------------------------------------------------------------------
        // 6. Lệnh Jump: JAL x1, 2000      (Mã máy: 7D0000EF)
        //----------------------------------------------------------------------
        instruction = 32'h7D0000EF; 
        #10;
        $display("[JAL]    jump=%b, reg_write=%b, imm=%d", 
                  jump, reg_write, $signed(imm));

        //----------------------------------------------------------------------
        // 7. Lệnh Atomic LR: LR.W x10, (x11) (Mã máy: 1005A52F)
        //----------------------------------------------------------------------
        instruction = 32'h1005A52F; 
        #10;
        $display("[LR.W]   mem_lr=%b, reg_write=%b, alu_ctrl=%b", 
                  mem_lr, reg_write, alu_control);

        //----------------------------------------------------------------------
        // 8. Lệnh Atomic SC: SC.W x12, x13, (x11) (Mã máy: 18D5A62F)
        //----------------------------------------------------------------------
        instruction = 32'h18D5A62F; 
        #10;
        $display("[SC.W]   mem_sc=%b, reg_write=%b, rs2=%d", 
                  mem_sc, reg_write, rs2_addr);

        //----------------------------------------------------------------------
        // 9. Lệnh Atomic AMOADD: AMOADD.W x14, x15, (x11) (Mã máy: 00F5A72F)
        //----------------------------------------------------------------------
        instruction = 32'h00F5A72F; 
        #10;
        $display("[AMOADD] mem_amo=%b, amo_op=%d, reg_write=%b", 
                  mem_amo, amo_op, reg_write);

        //----------------------------------------------------------------------
        // 10. Trạng thái NOP / Không hợp lệ
        //----------------------------------------------------------------------
        instruction = 32'h00000000;
        #10;

        $display("=========================================================================");
        $display("TESTBENCH COMPLETED SUCCESFULLY - OPEN GTKWAVE TO VIEW WAVEFORM");
        $display("=========================================================================");
        $finish;
    end

endmodule

tb/pipline_reg_tb/control_unit_waveform.vcd
$date
	Thu Jun 18 21:17:39 2026
$end
$version
	Icarus Verilog
$end
$timescale
	1ps
$end
$scope module tb_control_unit $end
$var wire 5 ! rs2_addr [4:0] $end
$var wire 5 " rs1_addr [4:0] $end
$var wire 1 # reg_write $end
$var wire 5 $ rd_addr [4:0] $end
$var wire 1 % mem_write $end
$var wire 1 & mem_to_reg $end
$var wire 1 ' mem_sc $end
$var wire 1 ( mem_read $end
$var wire 1 ) mem_lr $end
$var wire 1 * mem_amo $end
$var wire 1 + lui $end
$var wire 1 , jump $end
$var wire 1 - jalr $end
$var wire 32 . imm [31:0] $end
$var wire 3 / branch_type [2:0] $end
$var wire 1 0 branch $end
$var wire 1 1 auipc $end
$var wire 4 2 amo_op [3:0] $end
$var wire 1 3 alu_src $end
$var wire 4 4 alu_control [3:0] $end
$var reg 32 5 instruction [31:0] $end
$scope module uut $end
$var wire 32 6 instruction [31:0] $end
$var wire 5 7 rs2_addr [4:0] $end
$var wire 5 8 rs1_addr [4:0] $end
$var wire 5 9 rd_addr [4:0] $end
$var wire 7 : opcode [6:0] $end
$var wire 7 ; funct7 [6:0] $end
$var wire 5 < funct5 [4:0] $end
$var wire 3 = funct3 [2:0] $end
$var parameter 4 > ALU_ADD $end
$var parameter 4 ? ALU_AND $end
$var parameter 4 @ ALU_OR $end
$var parameter 4 A ALU_SLL $end
$var parameter 4 B ALU_SLT $end
$var parameter 4 C ALU_SRL $end
$var parameter 4 D ALU_SUB $end
$var parameter 4 E ALU_XOR $end
$var parameter 7 F OP_AMO $end
$var parameter 7 G OP_AUIPC $end
$var parameter 7 H OP_BRANCH $end
$var parameter 7 I OP_I_TYPE $end
$var parameter 7 J OP_JAL $end
$var parameter 7 K OP_JALR $end
$var parameter 7 L OP_LOAD $end
$var parameter 7 M OP_LUI $end
$var parameter 7 N OP_R_TYPE $end
$var parameter 7 O OP_STORE $end
$var reg 4 P alu_control [3:0] $end
$var reg 1 3 alu_src $end
$var reg 4 Q amo_op [3:0] $end
$var reg 1 1 auipc $end
$var reg 1 0 branch $end
$var reg 3 R branch_type [2:0] $end
$var reg 32 S imm [31:0] $end
$var reg 1 - jalr $end
$var reg 1 , jump $end
$var reg 1 + lui $end
$var reg 1 * mem_amo $end
$var reg 1 ) mem_lr $end
$var reg 1 ( mem_read $end
$var reg 1 ' mem_sc $end
$var reg 1 & mem_to_reg $end
$var reg 1 % mem_write $end
$var reg 1 # reg_write $end
$upscope $end
$upscope $end
$enddefinitions $end
$comment Show the parameter values. $end
$dumpall
b100011 O
b110011 N
b110111 M
b11 L
b1100111 K
b1101111 J
b10011 I
b1100011 H
b10111 G
b101111 F
b100 E
b110 D
b101 C
b111 B
b11 A
b1 @
b0 ?
b10 >
$end
#0
$dumpvars
b0 S
b0 R
b0 Q
b10 P
b0 =
b0 <
b0 ;
b110011 :
b11 9
b1 8
b10 7
b1000001000000110110011 6
b1000001000000110110011 5
b10 4
03
b0 2
01
00
b0 /
b0 .
0-
0,
0+
0*
0)
0(
0'
0&
0%
b11 $
1#
b1 "
b10 !
$end
#10000
13
1#
b11111111111111111111111111110110 .
b11111111111111111111111111110110 S
b10011 :
b1111111 ;
b11111 <
b100 "
b100 8
b10110 !
b10110 7
b101 $
b101 9
b11111111011000100000001010010011 5
b11111111011000100000001010010011 6
#20000
1&
1(
13
1#
b100 .
b100 S
b11 :
b10 =
b0 ;
b0 <
b101 "
b101 8
b100 !
b100 7
b110 $
b110 9
b10000101010001100000011 5
b10000101010001100000011 6
#30000
1%
0&
0(
13
0#
b1000 .
b1000 S
b100011 :
b111 !
b111 7
b1000 $
b1000 9
b11100101010010000100011 5
b11100101010010000100011 6
#40000
b1 /
b1 R
10
b110 4
b110 P
0%
03
b10000 .
b10000 S
b1100011 :
b1 =
b1 "
b1 8
b10 !
b10 7
b10000 $
b10000 9
b1000001001100001100011 5
b1000001001100001100011 6
#50000
1,
1#
b0 /
b0 R
00
b10 4
b10 P
b11111010000 .
b11111010000 S
b1101111 :
b0 =
b111110 ;
b1111 <
b0 "
b0 8
b10000 !
b10000 7
b1 $
b1 9
b1111101000000000000000011101111 5
b1111101000000000000000011101111 6
#60000
1)
13
0,
1#
b0 .
b0 S
b101111 :
b10 =
b1000 ;
b10 <
b1011 "
b1011 8
b0 !
b0 7
b1010 $
b1010 9
b10000000001011010010100101111 5
b10000000001011010010100101111 6
#70000
1'
0)
13
1#
b1100 ;
b11 <
b1101 !
b1101 7
b1100 $
b1100 9
b11000110101011010011000101111 5
b11000110101011010011000101111 6
#80000
b1 2
b1 Q
1*
0'
13
1#
b0 ;
b0 <
b1111 !
b1111 7
b1110 $
b1110 9
b111101011010011100101111 5
b111101011010011100101111 6
#90000
b0 2
b0 Q
0*
03
0#
b0 :
b0 =
b0 "
b0 8
b0 !
b0 7
b0 $
b0 9
b0 5
b0 6
