rtl/core/pipeline_register/id_ex.v
`timescale 1ns / 1ps
module id_ex (
    input wire clk, reset, clear, hold,
    input wire        id_valid,
    input wire [31:0] id_pc, id_rs1_data, id_rs2_data, id_imm,
    input wire [ 4:0] id_rs1_addr, id_rs2_addr, id_rd_addr,
    input wire [ 3:0] id_alu_control,
    input wire [ 2:0] id_branch_type,
    input wire [ 3:0] id_amo_op,
    input wire        id_reg_write, id_alu_src, id_mem_read, id_mem_write, id_mem_to_reg,
    input wire        id_branch, id_jump, id_jalr, id_lui, id_auipc, id_mem_lr, id_mem_sc, id_mem_amo,

    output reg        ex_valid,
    output reg [31:0] ex_pc, ex_rs1_data, ex_rs2_data, ex_imm,
    output reg [ 4:0] ex_rs1_addr, ex_rs2_addr, ex_rd_addr,
    output reg [ 3:0] ex_alu_control,
    output reg [ 2:0] ex_branch_type,
    output reg [ 3:0] ex_amo_op,
    output reg        ex_reg_write, ex_alu_src, ex_mem_read, ex_mem_write, ex_mem_to_reg,
    output reg        ex_branch, ex_jump, ex_jalr, ex_lui, ex_auipc, ex_mem_lr, ex_mem_sc, ex_mem_amo
);
    always @(posedge clk or posedge reset) begin
        if (reset || clear) begin
            ex_valid <= 1'b0; ex_pc <= 32'd0; ex_rs1_data <= 32'd0; ex_rs2_data <= 32'd0; ex_imm <= 32'd0;
            ex_rs1_addr <= 5'd0; ex_rs2_addr <= 5'd0; ex_rd_addr <= 5'd0; ex_alu_control <= 4'd0;
            ex_branch_type <= 3'd0; ex_amo_op <= 4'd0; ex_reg_write <= 1'b0; ex_alu_src <= 1'b0;
            ex_mem_read <= 1'b0; ex_mem_write <= 1'b0; ex_mem_to_reg <= 1'b0; ex_branch <= 1'b0;
            ex_jump <= 1'b0; ex_jalr <= 1'b0; ex_lui <= 1'b0; ex_auipc <= 1'b0; ex_mem_lr <= 1'b0;
            ex_mem_sc <= 1'b0; ex_mem_amo <= 1'b0;
        end else if (!hold) begin
            ex_valid <= id_valid; ex_pc <= id_pc; ex_rs1_data <= id_rs1_data; ex_rs2_data <= id_rs2_data; ex_imm <= id_imm;
            ex_rs1_addr <= id_rs1_addr; ex_rs2_addr <= id_rs2_addr; ex_rd_addr <= id_rd_addr; ex_alu_control <= id_alu_control;
            ex_branch_type <= id_branch_type; ex_amo_op <= id_amo_op;
            ex_reg_write <= id_valid ? id_reg_write : 1'b0;
            ex_alu_src <= id_valid ? id_alu_src : 1'b0;
            ex_mem_read <= id_valid ? id_mem_read : 1'b0;
            ex_mem_write <= id_valid ? id_mem_write : 1'b0;
            ex_mem_to_reg <= id_valid ? id_mem_to_reg : 1'b0;
            ex_branch <= id_valid ? id_branch : 1'b0;
            ex_jump <= id_valid ? id_jump : 1'b0;
            ex_jalr <= id_valid ? id_jalr : 1'b0;
            ex_lui <= id_valid ? id_lui : 1'b0;
            ex_auipc <= id_valid ? id_auipc : 1'b0;
            ex_mem_lr <= id_valid ? id_mem_lr : 1'b0;
            ex_mem_sc <= id_valid ? id_mem_sc : 1'b0;
            ex_mem_amo <= id_valid ? id_mem_amo : 1'b0;
        end
    end
endmodule

tb/pipline_reg_tb/tb_id_ex.v
`timescale 1ns / 1ps

module tb_id_ex;

    reg clk, reset, clear, hold;

    reg         id_valid;
    reg [31:0]  id_pc, id_rs1_data, id_rs2_data, id_imm;
    reg [4:0]   id_rs1_addr, id_rs2_addr, id_rd_addr;
    reg [3:0]   id_alu_control;
    reg [2:0]   id_branch_type;
    reg [3:0]   id_amo_op;
    reg         id_reg_write, id_alu_src, id_mem_read, id_mem_write, id_mem_to_reg;
    reg         id_branch, id_jump, id_jalr, id_lui, id_auipc;
    reg         id_mem_lr, id_mem_sc, id_mem_amo;

    wire        ex_valid;
    wire [31:0] ex_pc, ex_rs1_data, ex_rs2_data, ex_imm;
    wire [4:0]  ex_rs1_addr, ex_rs2_addr, ex_rd_addr;
    wire [3:0]  ex_alu_control;
    wire [2:0]  ex_branch_type;
    wire [3:0]  ex_amo_op;
    wire        ex_reg_write, ex_alu_src, ex_mem_read, ex_mem_write, ex_mem_to_reg;
    wire        ex_branch, ex_jump, ex_jalr, ex_lui, ex_auipc;
    wire        ex_mem_lr, ex_mem_sc, ex_mem_amo;

    id_ex dut (
        .clk(clk), .reset(reset), .clear(clear), .hold(hold),
        .id_valid(id_valid),
        .id_pc(id_pc),
        .id_rs1_data(id_rs1_data),
        .id_rs2_data(id_rs2_data),
        .id_imm(id_imm),
        .id_rs1_addr(id_rs1_addr),
        .id_rs2_addr(id_rs2_addr),
        .id_rd_addr(id_rd_addr),
        .id_alu_control(id_alu_control),
        .id_branch_type(id_branch_type),
        .id_amo_op(id_amo_op),
        .id_reg_write(id_reg_write),
        .id_alu_src(id_alu_src),
        .id_mem_read(id_mem_read),
        .id_mem_write(id_mem_write),
        .id_mem_to_reg(id_mem_to_reg),
        .id_branch(id_branch),
        .id_jump(id_jump),
        .id_jalr(id_jalr),
        .id_lui(id_lui),
        .id_auipc(id_auipc),
        .id_mem_lr(id_mem_lr),
        .id_mem_sc(id_mem_sc),
        .id_mem_amo(id_mem_amo),

        .ex_valid(ex_valid),
        .ex_pc(ex_pc),
        .ex_rs1_data(ex_rs1_data),
        .ex_rs2_data(ex_rs2_data),
        .ex_imm(ex_imm),
        .ex_rs1_addr(ex_rs1_addr),
        .ex_rs2_addr(ex_rs2_addr),
        .ex_rd_addr(ex_rd_addr),
        .ex_alu_control(ex_alu_control),
        .ex_branch_type(ex_branch_type),
        .ex_amo_op(ex_amo_op),
        .ex_reg_write(ex_reg_write),
        .ex_alu_src(ex_alu_src),
        .ex_mem_read(ex_mem_read),
        .ex_mem_write(ex_mem_write),
        .ex_mem_to_reg(ex_mem_to_reg),
        .ex_branch(ex_branch),
        .ex_jump(ex_jump),
        .ex_jalr(ex_jalr),
        .ex_lui(ex_lui),
        .ex_auipc(ex_auipc),
        .ex_mem_lr(ex_mem_lr),
        .ex_mem_sc(ex_mem_sc),
        .ex_mem_amo(ex_mem_amo)
    );

    always #5 clk = ~clk;

    initial begin
        $dumpfile("id_ex.vcd");
        $dumpvars(0, tb_id_ex);

        clk = 0;
        reset = 1;
        clear = 0;
        hold = 0;

        #10 reset = 0;

        id_valid = 1;
        id_pc = 32'h1000;
        id_rs1_data = 32'd10;
        id_rs2_data = 32'd20;
        id_imm = 32'd4;
        id_rs1_addr = 5'd1;
        id_rs2_addr = 5'd2;
        id_rd_addr = 5'd3;
        id_alu_control = 4'd1;
        id_branch_type = 3'd0;
        id_amo_op = 4'd0;
        id_reg_write = 1;
        id_alu_src = 1;
        id_mem_read = 0;
        id_mem_write = 0;
        id_mem_to_reg = 0;
        id_branch = 0;
        id_jump = 0;
        id_jalr = 0;
        id_lui = 0;
        id_auipc = 0;
        id_mem_lr = 0;
        id_mem_sc = 0;
        id_mem_amo = 0;

        #10;

        hold = 1;
        id_pc = 32'h2000;

        #10;

        hold = 0;

        #10;

        clear = 1;

        #10;

        clear = 0;

        #10;

        $finish;
    end

endmodule

tb/pipline_reg_tb/id_ex.vcd
$date
	Wed Jun 17 21:21:38 2026
$end
$version
	Icarus Verilog
$end
$timescale
	1ps
$end
$scope module tb_id_ex $end
$var wire 1 ! ex_valid $end
$var wire 32 " ex_rs2_data [31:0] $end
$var wire 5 # ex_rs2_addr [4:0] $end
$var wire 32 $ ex_rs1_data [31:0] $end
$var wire 5 % ex_rs1_addr [4:0] $end
$var wire 1 & ex_reg_write $end
$var wire 5 ' ex_rd_addr [4:0] $end
$var wire 32 ( ex_pc [31:0] $end
$var wire 1 ) ex_mem_write $end
$var wire 1 * ex_mem_to_reg $end
$var wire 1 + ex_mem_sc $end
$var wire 1 , ex_mem_read $end
$var wire 1 - ex_mem_lr $end
$var wire 1 . ex_mem_amo $end
$var wire 1 / ex_lui $end
$var wire 1 0 ex_jump $end
$var wire 1 1 ex_jalr $end
$var wire 32 2 ex_imm [31:0] $end
$var wire 3 3 ex_branch_type [2:0] $end
$var wire 1 4 ex_branch $end
$var wire 1 5 ex_auipc $end
$var wire 4 6 ex_amo_op [3:0] $end
$var wire 1 7 ex_alu_src $end
$var wire 4 8 ex_alu_control [3:0] $end
$var reg 1 9 clear $end
$var reg 1 : clk $end
$var reg 1 ; hold $end
$var reg 4 < id_alu_control [3:0] $end
$var reg 1 = id_alu_src $end
$var reg 4 > id_amo_op [3:0] $end
$var reg 1 ? id_auipc $end
$var reg 1 @ id_branch $end
$var reg 3 A id_branch_type [2:0] $end
$var reg 32 B id_imm [31:0] $end
$var reg 1 C id_jalr $end
$var reg 1 D id_jump $end
$var reg 1 E id_lui $end
$var reg 1 F id_mem_amo $end
$var reg 1 G id_mem_lr $end
$var reg 1 H id_mem_read $end
$var reg 1 I id_mem_sc $end
$var reg 1 J id_mem_to_reg $end
$var reg 1 K id_mem_write $end
$var reg 32 L id_pc [31:0] $end
$var reg 5 M id_rd_addr [4:0] $end
$var reg 1 N id_reg_write $end
$var reg 5 O id_rs1_addr [4:0] $end
$var reg 32 P id_rs1_data [31:0] $end
$var reg 5 Q id_rs2_addr [4:0] $end
$var reg 32 R id_rs2_data [31:0] $end
$var reg 1 S id_valid $end
$var reg 1 T reset $end
$scope module dut $end
$var wire 1 9 clear $end
$var wire 1 : clk $end
$var wire 1 ; hold $end
$var wire 4 U id_alu_control [3:0] $end
$var wire 1 = id_alu_src $end
$var wire 4 V id_amo_op [3:0] $end
$var wire 1 ? id_auipc $end
$var wire 1 @ id_branch $end
$var wire 3 W id_branch_type [2:0] $end
$var wire 32 X id_imm [31:0] $end
$var wire 1 C id_jalr $end
$var wire 1 D id_jump $end
$var wire 1 E id_lui $end
$var wire 1 F id_mem_amo $end
$var wire 1 G id_mem_lr $end
$var wire 1 H id_mem_read $end
$var wire 1 I id_mem_sc $end
$var wire 1 J id_mem_to_reg $end
$var wire 1 K id_mem_write $end
$var wire 32 Y id_pc [31:0] $end
$var wire 5 Z id_rd_addr [4:0] $end
$var wire 1 N id_reg_write $end
$var wire 5 [ id_rs1_addr [4:0] $end
$var wire 32 \ id_rs1_data [31:0] $end
$var wire 5 ] id_rs2_addr [4:0] $end
$var wire 32 ^ id_rs2_data [31:0] $end
$var wire 1 S id_valid $end
$var wire 1 T reset $end
$var reg 4 _ ex_alu_control [3:0] $end
$var reg 1 7 ex_alu_src $end
$var reg 4 ` ex_amo_op [3:0] $end
$var reg 1 5 ex_auipc $end
$var reg 1 4 ex_branch $end
$var reg 3 a ex_branch_type [2:0] $end
$var reg 32 b ex_imm [31:0] $end
$var reg 1 1 ex_jalr $end
$var reg 1 0 ex_jump $end
$var reg 1 / ex_lui $end
$var reg 1 . ex_mem_amo $end
$var reg 1 - ex_mem_lr $end
$var reg 1 , ex_mem_read $end
$var reg 1 + ex_mem_sc $end
$var reg 1 * ex_mem_to_reg $end
$var reg 1 ) ex_mem_write $end
$var reg 32 c ex_pc [31:0] $end
$var reg 5 d ex_rd_addr [4:0] $end
$var reg 1 & ex_reg_write $end
$var reg 5 e ex_rs1_addr [4:0] $end
$var reg 32 f ex_rs1_data [31:0] $end
$var reg 5 g ex_rs2_addr [4:0] $end
$var reg 32 h ex_rs2_data [31:0] $end
$var reg 1 ! ex_valid $end
$upscope $end
$upscope $end
$enddefinitions $end
$comment Show the parameter values. $end
$dumpall
$end
#0
$dumpvars
b0 h
b0 g
b0 f
b0 e
b0 d
b0 c
b0 b
b0 a
b0 `
b0 _
bx ^
bx ]
bx \
bx [
bx Z
bx Y
bx X
bx W
bx V
bx U
1T
xS
bx R
bx Q
bx P
bx O
xN
bx M
bx L
xK
xJ
xI
xH
xG
xF
xE
xD
xC
bx B
bx A
x@
x?
bx >
x=
bx <
0;
0:
09
b0 8
07
b0 6
05
04
b0 3
b0 2
01
00
0/
0.
0-
0,
0+
0*
0)
b0 (
b0 '
0&
b0 %
b0 $
b0 #
b0 "
0!
$end
#5000
1:
#10000
0:
0F
0I
0G
0?
0E
0C
0D
0@
0J
0K
0H
1=
1N
b0 >
b0 V
b0 A
b0 W
b1 <
b1 U
b11 M
b11 Z
b10 Q
b10 ]
b1 O
b1 [
b100 B
b100 X
b10100 R
b10100 ^
b1010 P
b1010 \
b1000000000000 L
b1000000000000 Y
1S
0T
#15000
17
1&
b1 8
b1 _
b11 '
b11 d
b10 #
b10 g
b1 %
b1 e
b100 2
b100 b
b10100 "
b10100 h
b1010 $
b1010 f
b1000000000000 (
b1000000000000 c
1!
1:
#20000
0:
b10000000000000 L
b10000000000000 Y
1;
#25000
1:
#30000
0:
0;
#35000
b10000000000000 (
b10000000000000 c
1:
#40000
0:
19
#45000
07
0&
b0 8
b0 _
b0 '
b0 d
b0 #
b0 g
b0 %
b0 e
b0 2
b0 b
b0 "
b0 h
b0 $
b0 f
b0 (
b0 c
0!
1:
#50000
0:
09
#55000
17
1&
b1 8
b1 _
b11 '
b11 d
b10 #
b10 g
b1 %
b1 e
b100 2
b100 b
b10100 "
b10100 h
b1010 $
b1010 f
b10000000000000 (
b10000000000000 c
1!
1:
