rtl/core/pipeline_register/if_id.v
`timescale 1ns / 1ps
module if_id (
    input wire clk,
    input wire reset,
    input wire clear,
    input wire hold,
    input wire [31:0] if_pc,
    input wire [31:0] if_instr,
    
    output reg        id_valid,
    output reg [31:0] id_pc,
    output reg [31:0] id_instr
);
    always @(posedge clk or posedge reset) begin
        if (reset || clear) begin
            id_valid <= 1'b0;
            id_pc    <= 32'd0;
            id_instr <= 32'd0;
        end else if (!hold) begin
            id_valid <= 1'b1;
            id_pc    <= if_pc;
            id_instr <= if_instr;
        end
    end
endmodule

tb/pipline_reg_tb/tb_if_id.v
`timescale 1ns / 1ps

module tb_if_id;

    reg clk;
    reg reset;
    reg clear;
    reg hold;

    reg [31:0] if_pc;
    reg [31:0] if_instr;

    wire id_valid;
    wire [31:0] id_pc;
    wire [31:0] id_instr;

    // DUT = Device Under Test
    if_id dut (
        .clk(clk),
        .reset(reset),
        .clear(clear),
        .hold(hold),
        .if_pc(if_pc),
        .if_instr(if_instr),
        .id_valid(id_valid),
        .id_pc(id_pc),
        .id_instr(id_instr)
    );

    // Clock 10ns
    always #5 clk = ~clk;

    initial begin

        $dumpfile("if_id.vcd");
        $dumpvars(0, tb_if_id);

        clk = 0;
        reset = 1;
        clear = 0;
        hold = 0;
        if_pc = 0;
        if_instr = 0;

        #10;

        // bỏ reset
        reset = 0;

        // instruction 1
        if_pc = 32'h00000000;
        if_instr = 32'h11111111;

        #10;

        // instruction 2
        if_pc = 32'h00000004;
        if_instr = 32'h22222222;

        #10;

        // test stall
        hold = 1;

        if_pc = 32'h00000008;
        if_instr = 32'h33333333;

        #10;

        // bỏ stall
        hold = 0;

        #10;

        // test flush
        clear = 1;

        #10;

        clear = 0;

        #10;

        $finish;
    end

endmodule

tb/pipline_reg_tb/if_id.vcd
$date
	Wed Jun 17 21:10:46 2026
$end
$version
	Icarus Verilog
$end
$timescale
	1ps
$end
$scope module tb_if_id $end
$var wire 1 ! id_valid $end
$var wire 32 " id_pc [31:0] $end
$var wire 32 # id_instr [31:0] $end
$var reg 1 $ clear $end
$var reg 1 % clk $end
$var reg 1 & hold $end
$var reg 32 ' if_instr [31:0] $end
$var reg 32 ( if_pc [31:0] $end
$var reg 1 ) reset $end
$scope module dut $end
$var wire 1 $ clear $end
$var wire 1 % clk $end
$var wire 1 & hold $end
$var wire 32 * if_instr [31:0] $end
$var wire 32 + if_pc [31:0] $end
$var wire 1 ) reset $end
$var reg 32 , id_instr [31:0] $end
$var reg 32 - id_pc [31:0] $end
$var reg 1 ! id_valid $end
$upscope $end
$upscope $end
$enddefinitions $end
$comment Show the parameter values. $end
$dumpall
$end
#0
$dumpvars
b0 -
b0 ,
b0 +
b0 *
1)
b0 (
b0 '
0&
0%
0$
b0 #
b0 "
0!
$end
#5000
1%
#10000
0%
b10001000100010001000100010001 '
b10001000100010001000100010001 *
0)
#15000
b10001000100010001000100010001 #
b10001000100010001000100010001 ,
1!
1%
#20000
0%
b100010001000100010001000100010 '
b100010001000100010001000100010 *
b100 (
b100 +
#25000
b100010001000100010001000100010 #
b100010001000100010001000100010 ,
b100 "
b100 -
1%
#30000
0%
b110011001100110011001100110011 '
b110011001100110011001100110011 *
b1000 (
b1000 +
1&
#35000
1%
#40000
0%
0&
#45000
b110011001100110011001100110011 #
b110011001100110011001100110011 ,
b1000 "
b1000 -
1%
#50000
0%
1$
#55000
b0 #
b0 ,
b0 "
b0 -
0!
1%
#60000
0%
0$
#65000
b110011001100110011001100110011 #
b110011001100110011001100110011 ,
b1000 "
b1000 -
1!
1%
