rtl/core/alu.v
module alu (
    input      [31:0] a,
    input      [31:0] b,
    input      [ 3:0] alu_control,
    output reg [31:0] result,
    output            zero
);

  // Định nghĩa các mã điều khiển (Dựa trên chuẩn thông dụng cho RV32I)
  localparam AND = 4'b0000;
  localparam OR = 4'b0001;
  localparam ADD = 4'b0010;
  localparam SUB = 4'b0110;
  localparam XOR = 4'b0100;
  localparam SRL = 4'b0101;  // Shift Right Logical
  localparam SLL = 4'b0011;  // Shift Left Logical
  localparam SLT = 4'b0111;  // Set Less Than (có dấu)

  always @(*) begin
    case (alu_control)
      ADD: result = a + b;
      SUB: result = a - b;
      AND: result = a & b;
      OR: result = a | b;
      XOR: result = a ^ b;
      SLL: result = a << b[4:0];  // Chỉ lấy 5 bit thấp của b để dịch
      SRL: result = a >> b[4:0];
      SLT: result = ($signed(a) < $signed(b)) ? 32'd1 : 32'd0;
      default: result = 32'b0;
    endcase
  end

  // Cờ Zero: bật lên 1 nếu kết quả bằng 0 (phục vụ lệnh BEQ, BNE...)
  assign zero = (result == 32'b0);

endmodule

tb/alu_tb.v
`timescale 1ns / 1ps

module alu_tb();

    // 1. Khai báo các biến kết nối với ALU
    reg  [31:0] a;
    reg  [31:0] b;
    reg  [3:0]  alu_control;
    wire [31:0] result;
    wire        zero;

    // 2. Khởi tạo module ALU (DUT - Device Under Test)
    alu dut (
        .a(a),
        .b(b),
        .alu_control(alu_control),
        .result(result),
        .zero(zero)
    );

    // Định nghĩa lại các mã lệnh để dễ đọc trong testbench
    localparam AND  = 4'b0000;
    localparam OR   = 4'b0001;
    localparam ADD  = 4'b0010;
    localparam SLL  = 4'b0011;
    localparam XOR  = 4'b0100;
    localparam SRL  = 4'b0101;
    localparam SUB  = 4'b0110;
    localparam SLT  = 4'b0111;

    // 3. Quy trình kiểm thử
    initial begin
        $dumpfile("tb/alu_tb.vcd"); // Đặt tên file xuất sóng
        $dumpvars(0, alu_tb);       // Ghi lại tất cả biến trong module alu_tb

        // Hiển thị tiêu đề bảng kết quả (được căn lề hoàn hảo)
        $display("Time (ns) |       A (Hex) [Signed Dec]       |       B (Hex) [Signed Dec]       | Control  |    Result (Hex) [Signed Dec]     | Zero");
        $display("----------|----------------------------------|----------------------------------|----------|----------------------------------|------");

        // Test Case 1: Phép cộng (ADD)
        a = 32'd10; b = 32'd20; alu_control = ADD;
        #10;
        $display("%9d | 0x%08h (%11d) | 0x%08h (%11d) |   ADD    | 0x%08h (%11d) |  %b  ", $time, a, $signed(a), b, $signed(b), result, $signed(result), zero);

        // Test Case 2: Phép trừ (SUB) dẫn đến kết quả bằng 0
        a = 32'd50; b = 32'd50; alu_control = SUB;
        #10;
        $display("%9d | 0x%08h (%11d) | 0x%08h (%11d) |   SUB    | 0x%08h (%11d) |  %b  ", $time, a, $signed(a), b, $signed(b), result, $signed(result), zero);

        // Test Case 3: Phép toán logic AND
        a = 32'hAAAA_AAAA; b = 32'h5555_5555; alu_control = AND;
        #10;
        $display("%9d | 0x%08h (%11d) | 0x%08h (%11d) |   AND    | 0x%08h (%11d) |  %b  ", $time, a, $signed(a), b, $signed(b), result, $signed(result), zero);

        // Test Case 4: So sánh nhỏ hơn (SLT) - Số dương
        a = 32'd15; b = 32'd25; alu_control = SLT;
        #10;
        $display("%9d | 0x%08h (%11d) | 0x%08h (%11d) |   SLT    | 0x%08h (%11d) |  %b  ", $time, a, $signed(a), b, $signed(b), result, $signed(result), zero);

        // Test Case 5: So sánh nhỏ hơn (SLT) - Số âm (Kiểm tra tính đúng đắn của $signed)
        a = -32'd10; b = 32'd5; alu_control = SLT;
        #10;
        $display("%9d | 0x%08h (%11d) | 0x%08h (%11d) |   SLT    | 0x%08h (%11d) |  %b  ", $time, a, $signed(a), b, $signed(b), result, $signed(result), zero);

        // Test Case 6: Phép toán logic OR
        a = 32'hF0F0_FFFF; b = 32'h0F0F_0000; alu_control = OR;
        #10;
        $display("%9d | 0x%08h (%11d) | 0x%08h (%11d) |    OR    | 0x%08h (%11d) |  %b  ", $time, a, $signed(a), b, $signed(b), result, $signed(result), zero);

        // Test Case 7: Phép toán logic XOR
        a = 32'hF0F0_FFFF; b = 32'hFFFF_0000; alu_control = XOR;
        #10;
        $display("%9d | 0x%08h (%11d) | 0x%08h (%11d) |   XOR    | 0x%08h (%11d) |  %b  ", $time, a, $signed(a), b, $signed(b), result, $signed(result), zero);

        // Test Case 8: Dịch trái logic (SLL) - dịch 4 bit
        a = 32'h0000_000F; b = 32'd4; alu_control = SLL;
        #10;
        $display("%9d | 0x%08h (%11d) | 0x%08h (%11d) |   SLL    | 0x%08h (%11d) |  %b  ", $time, a, $signed(a), b, $signed(b), result, $signed(result), zero);

        // Test Case 9: Dịch phải logic (SRL) - dịch 4 bit
        a = 32'hF000_0000; b = 32'd4; alu_control = SRL;
        #10;
        $display("%9d | 0x%08h (%11d) | 0x%08h (%11d) |   SRL    | 0x%08h (%11d) |  %b  ", $time, a, $signed(a), b, $signed(b), result, $signed(result), zero);

        $display("----------|----------------------------------|----------------------------------|----------|----------------------------------|------");
        $display("Kiem tra ket thuc.");
        $finish; // Dừng mô phỏng
    end

endmodule

tb/alu_tb.vcd
$date
	Thu Jun 18 21:59:42 2026
$end
$version
	Icarus Verilog
$end
$timescale
	1ps
$end
$scope module alu_tb $end
$var wire 1 ! zero $end
$var wire 32 " result [31:0] $end
$var parameter 4 # ADD $end
$var parameter 4 $ AND $end
$var parameter 4 % OR $end
$var parameter 4 & SLL $end
$var parameter 4 ' SLT $end
$var parameter 4 ( SRL $end
$var parameter 4 ) SUB $end
$var parameter 4 * XOR $end
$var reg 32 + a [31:0] $end
$var reg 4 , alu_control [3:0] $end
$var reg 32 - b [31:0] $end
$scope module dut $end
$var wire 32 . a [31:0] $end
$var wire 4 / alu_control [3:0] $end
$var wire 32 0 b [31:0] $end
$var wire 1 ! zero $end
$var parameter 4 1 ADD $end
$var parameter 4 2 AND $end
$var parameter 4 3 OR $end
$var parameter 4 4 SLL $end
$var parameter 4 5 SLT $end
$var parameter 4 6 SRL $end
$var parameter 4 7 SUB $end
$var parameter 4 8 XOR $end
$var reg 32 9 result [31:0] $end
$upscope $end
$upscope $end
$enddefinitions $end
$comment Show the parameter values. $end
$dumpall
b100 8
b110 7
b101 6
b111 5
b11 4
b1 3
b0 2
b10 1
b100 *
b110 )
b101 (
b111 '
b11 &
b1 %
b0 $
b10 #
$end
#0
$dumpvars
b11110 9
b10100 0
b10 /
b1010 .
b10100 -
b10 ,
b1010 +
b11110 "
0!
$end
#10000
1!
b0 "
b0 9
b110 ,
b110 /
b110010 -
b110010 0
b110010 +
b110010 .
#20000
b0 ,
b0 /
b1010101010101010101010101010101 -
b1010101010101010101010101010101 0
b10101010101010101010101010101010 +
b10101010101010101010101010101010 .
#30000
0!
b1 "
b1 9
b111 ,
b111 /
b11001 -
b11001 0
b1111 +
b1111 .
#40000
b101 -
b101 0
b11111111111111111111111111110110 +
b11111111111111111111111111110110 .
#50000
b11111111111111111111111111111111 "
b11111111111111111111111111111111 9
b1 ,
b1 /
b1111000011110000000000000000 -
b1111000011110000000000000000 0
b11110000111100001111111111111111 +
b11110000111100001111111111111111 .
#60000
b1111000011111111111111111111 "
b1111000011111111111111111111 9
b100 ,
b100 /
b11111111111111110000000000000000 -
b11111111111111110000000000000000 0
#70000
b11110000 "
b11110000 9
b11 ,
b11 /
b100 -
b100 0
b1111 +
b1111 .
#80000
b1111000000000000000000000000 "
b1111000000000000000000000000 9
b101 ,
b101 /
b11110000000000000000000000000000 +
b11110000000000000000000000000000 .
